url_analyzer/LICENSE
url_analyzer/README.MD
url_analyzer/__init__.py
url_analyzer/requirements.txt
url_analyzer/thirdparty.json
url_analyzer-0.12.dist-info/LICENSE.rst
url_analyzer-0.12.dist-info/METADATA
url_analyzer-0.12.dist-info/WHEEL
url_analyzer-0.12.dist-info/top_level.txt
url_analyzer-0.12.dist-info/RECORD
